pytest_asyncio_concurrent/__init__.py
pytest_asyncio_concurrent/fixture_async.py
pytest_asyncio_concurrent/grouping.py
pytest_asyncio_concurrent/hooks.py
pytest_asyncio_concurrent/plugin.py
pytest_asyncio_concurrent-0.5.1.dist-info/licenses/LICENSE
pytest_asyncio_concurrent-0.5.1.dist-info/METADATA
pytest_asyncio_concurrent-0.5.1.dist-info/WHEEL
pytest_asyncio_concurrent-0.5.1.dist-info/entry_points.txt
pytest_asyncio_concurrent-0.5.1.dist-info/top_level.txt
pytest_asyncio_concurrent-0.5.1.dist-info/RECORD
