Metadata-Version: 2.4
Name: pytest-asyncio-concurrent
Version: 0.5.1
Summary: Pytest plugin to execute python async tests concurrently.
Author-email: Zane Chen <czl970721@gmail.com>
Maintainer-email: Zane Chen <czl970721@gmail.com>
License: 
Project-URL: Repository, https://github.com/czl9707/pytest-asyncio-concurrent
Project-URL: Homepage, https://github.com/czl9707/pytest-asyncio-concurrent
Project-URL: Issues, https://github.com/czl9707/pytest-asyncio-concurrent/issues
Classifier: Framework :: Pytest
Classifier: Development Status :: 4 - Beta
Classifier: Intended Audience :: Developers
Classifier: Topic :: Software Development :: Testing
Classifier: Operating System :: OS Independent
Classifier: Programming Language :: Python
Classifier: Programming Language :: Python :: 3.8
Classifier: Programming Language :: Python :: 3.9
Classifier: Programming Language :: Python :: 3.10
Classifier: Programming Language :: Python :: 3.11
Classifier: Programming Language :: Python :: 3.12
Classifier: Programming Language :: Python :: 3.13
Classifier: Programming Language :: Python :: 3 :: Only
Classifier: License :: OSI Approved :: MIT License
Requires-Python: >=3.8
License-File: LICENSE
Requires-Dist: pytest>=6.2.0
Provides-Extra: testing
Requires-Dist: coverage>=7.6.0; extra == "testing"
Dynamic: license-file
